pytest_data_loader/__init__.py
pytest_data_loader/compat.py
pytest_data_loader/constants.py
pytest_data_loader/plugin.py
pytest_data_loader/py.typed
pytest_data_loader/types.py
pytest_data_loader/utils.py
pytest_data_loader/loaders/__init__.py
pytest_data_loader/loaders/impl.py
pytest_data_loader/loaders/loaders.py
pytest_data_loader/loaders/reader.py
pytest_data_loader-0.7.0.dist-info/METADATA
pytest_data_loader-0.7.0.dist-info/WHEEL
pytest_data_loader-0.7.0.dist-info/entry_points.txt
pytest_data_loader-0.7.0.dist-info/top_level.txt
pytest_data_loader-0.7.0.dist-info/RECORD
