Metadata-Version: 2.4
Name: pytest-data-loader
Version: 0.7.0
Summary: Pytest plugin for loading test data for data-driven testing (DDT)
Author: Yugo Kato
Project-URL: Homepage, https://github.com/yugokato/pytest-data-loader
Keywords: pytest,data-driven testing,DDT
Classifier: Development Status :: 4 - Beta
Classifier: Framework :: Pytest
Classifier: Intended Audience :: Developers
Classifier: License :: OSI Approved :: MIT License
Classifier: Programming Language :: Python :: 3 :: Only
Classifier: Programming Language :: Python :: 3.10
Classifier: Programming Language :: Python :: 3.11
Classifier: Programming Language :: Python :: 3.12
Classifier: Programming Language :: Python :: 3.13
Classifier: Programming Language :: Python :: 3.14
Classifier: Topic :: Software Development :: Quality Assurance
Classifier: Topic :: Software Development :: Testing
Requires-Python: >=3.10
Requires-Dist: pytest<10,>=7.0.0
Requires-Dist: pluggy>=1.2.0
Requires-Dist: typing_extensions>=4.1.0; python_version < "3.11"
Provides-Extra: lint
Requires-Dist: mypy<2,>=1.15.0; extra == "lint"
Requires-Dist: pre-commit<5,>=3.0.0; extra == "lint"
Requires-Dist: ruff<0.15.0,>=0.14.0; extra == "lint"
Provides-Extra: test
Requires-Dist: pytest-mock<4,>=3.0.0; extra == "test"
Requires-Dist: pytest-smoke; extra == "test"
Requires-Dist: pytest-xdist[psutil]<4,>=2.3.0; extra == "test"
Requires-Dist: pandas>=2.0.0; extra == "test"
Requires-Dist: pypdf>=6.1.0; extra == "test"
Requires-Dist: pyyaml>=6.0.0; extra == "test"
Requires-Dist: tomli>=2.3.0; python_version < "3.11" and extra == "test"
Provides-Extra: dev
Requires-Dist: tox<5,>=4.0.0; extra == "dev"
Requires-Dist: tox-uv<2,>=1.0.0; extra == "dev"
Requires-Dist: pytest-data-loader[lint,test]; extra == "dev"
